stmpy/__init__.py
stmpy/cv.py
stmpy/driftcorr.py
stmpy/image.py
stmpy/io.py
stmpy/matio.py
stmpy/read_STMView.py
stmpy/read_all.py
stmpy/tools.py
stmpy/color/__init__.py
stmpy/color/colormap.py
stmpy/color/palette.py
stmpy/color/maps/ALS-og.txt
stmpy/color/maps/ALS.txt
stmpy/color/maps/Autumn.mat
stmpy/color/maps/Blue1.mat
stmpy/color/maps/Blue2.mat
stmpy/color/maps/Blue3.mat
stmpy/color/maps/Defect0.mat
stmpy/color/maps/Defect1.mat
stmpy/color/maps/Defect2.mat
stmpy/color/maps/Defect4.mat
stmpy/color/maps/Gray.mat
stmpy/color/maps/GrayInverse.mat
stmpy/color/maps/PuGn.txt
stmpy/color/maps/Red_Blue.txt
stmpy/color/maps/SailingMod2.mat
stmpy/color/maps/YH.mat
stmpy/color/maps/mhblue.mat
stmpy/hp/__init__.py
stmpy/hp/kondo_holes.py
stmpy/hp/tight_binding.py
stmpy/mapviewer/__init__.py
stmpy/mapviewer/gui_components.py
stmpy/mapviewer/helptext.txt
stmpy/mapviewer/misc.py
stmpy/mapviewer/view3ds.py
hoffmanstmpy-1.0.2.dist-info/LICENSE
hoffmanstmpy-1.0.2.dist-info/LICENSE.txt
hoffmanstmpy-1.0.2.dist-info/METADATA
hoffmanstmpy-1.0.2.dist-info/WHEEL
hoffmanstmpy-1.0.2.dist-info/top_level.txt
hoffmanstmpy-1.0.2.dist-info/RECORD
