Metadata-Version: 2.1
Name: hoffmanstmpy
Version: 1.0.2
Summary: Scanning tunneling microscopy data analysis suite
Home-page: https://github.com/hoffmanlabcoding/stmpy
Download-URL: https://github.com/hoffmanlabcoding/stmpy.git
Author: Harris Pirie
Author-email: hoffmanlabcoding@gmail.com
License: MIT
Keywords: STM,Python,Data Analysis
Classifier: Development Status :: 3 - Alpha
Classifier: Intended Audience :: Developers
Classifier: Topic :: Software Development :: Build Tools
Classifier: License :: OSI Approved :: MIT License
Classifier: Programming Language :: Python :: 3
License-File: LICENSE
License-File: LICENSE.txt
Requires-Dist: numpy
Requires-Dist: scipy
Requires-Dist: matplotlib
Requires-Dist: opencv-python
Requires-Dist: scikit-image
